clean_data/__init__.py
clean_data_Caelon-0.0.1.dist-info/LICENSE
clean_data_Caelon-0.0.1.dist-info/METADATA
clean_data_Caelon-0.0.1.dist-info/WHEEL
clean_data_Caelon-0.0.1.dist-info/top_level.txt
clean_data_Caelon-0.0.1.dist-info/RECORD
