Metadata-Version: 2.1
Name: clean-data-Caelon
Version: 0.0.1
Summary: A Class with 8 functions to clean datasets.
Home-page: https://github.com/pypa/sampleproject
Author: Caelon
Author-email: Caelon@example.com
License: UNKNOWN
Project-URL: Bug Tracker, https://github.com/pypa/sampleproject/issues
Platform: UNKNOWN
Classifier: Programming Language :: Python :: 3
Classifier: License :: OSI Approved :: MIT License
Classifier: Operating System :: OS Independent
Requires-Python: >=3.6
License-File: LICENSE
